whatsthedamage/__init__.py
whatsthedamage/__main__.py
whatsthedamage/app.py
whatsthedamage/cli_app.py
whatsthedamage/api/__init__.py
whatsthedamage/api/docs.py
whatsthedamage/api/error_handlers.py
whatsthedamage/api/helpers.py
whatsthedamage/api/v2/__init__.py
whatsthedamage/api/v2/endpoints.py
whatsthedamage/api/v2/schema.py
whatsthedamage/config/__init__.py
whatsthedamage/config/config.py
whatsthedamage/config/dt_models.py
whatsthedamage/config/flask_config.py
whatsthedamage/controllers/__init__.py
whatsthedamage/controllers/cli_controller.py
whatsthedamage/controllers/routes.py
whatsthedamage/controllers/routes_helpers.py
whatsthedamage/locale/en/LC_MESSAGES/messages.po
whatsthedamage/locale/hu/LC_MESSAGES/messages.po
whatsthedamage/models/__init__.py
whatsthedamage/models/api_models.py
whatsthedamage/models/csv_file_handler.py
whatsthedamage/models/csv_processor.py
whatsthedamage/models/csv_row.py
whatsthedamage/models/dt_calculators.py
whatsthedamage/models/dt_response_builder.py
whatsthedamage/models/machine_learning.py
whatsthedamage/models/row_enrichment.py
whatsthedamage/models/row_enrichment_ml.py
whatsthedamage/models/row_filter.py
whatsthedamage/models/rows_processor.py
whatsthedamage/scripts/README.md
whatsthedamage/scripts/ml_util.py
whatsthedamage/services/__init__.py
whatsthedamage/services/configuration_service.py
whatsthedamage/services/data_formatting_service.py
whatsthedamage/services/file_upload_service.py
whatsthedamage/services/processing_service.py
whatsthedamage/services/response_builder_service.py
whatsthedamage/services/session_service.py
whatsthedamage/services/validation_service.py
whatsthedamage/static/model-rf-v5alpha_en.joblib
whatsthedamage/static/model-rf-v5alpha_en.manifest.json
whatsthedamage/utils/__init__.py
whatsthedamage/utils/date_converter.py
whatsthedamage/utils/flask_locale.py
whatsthedamage/utils/validation.py
whatsthedamage/utils/version.py
whatsthedamage/view/__init__.py
whatsthedamage/view/forms.py
whatsthedamage-0.10.0.dist-info/licenses/LICENSE
whatsthedamage-0.10.0.dist-info/METADATA
whatsthedamage-0.10.0.dist-info/WHEEL
whatsthedamage-0.10.0.dist-info/entry_points.txt
whatsthedamage-0.10.0.dist-info/top_level.txt
whatsthedamage-0.10.0.dist-info/RECORD
