Metadata-Version: 2.4
Name: whatsthedamage
Version: 0.10.0
Summary: A package to process bank account exports in CSV files. With optionally a web interface.
Author-email: Balázs NÉMETH <balagetech@protonmail.com>
Maintainer-email: Balázs NÉMETH <balagetech@protonmail.com>
License-Expression: GPL-3.0-or-later
Project-URL: bugs, https://github.com/abalage/whatsthedamage/issues
Project-URL: changelog, https://github.com/abalage/whatsthedamage/blob/master/changelog.md
Project-URL: homepage, https://github.com/abalage/whatsthedamage
Keywords: csv,account,report,web
Classifier: Development Status :: 4 - Beta
Classifier: Programming Language :: Python :: 3
Classifier: Operating System :: OS Independent
Requires-Python: >=3.9
License-File: LICENSE
Requires-Dist: pandas==2.3.2
Requires-Dist: pydantic==2.11.9
Requires-Dist: python-magic==0.4.27
Requires-Dist: pyyaml==6.0.2
Requires-Dist: scikit-learn==1.7.2
Provides-Extra: dev
Requires-Dist: pip-tools==7.5.0; extra == "dev"
Requires-Dist: babel==2.17.0; extra == "dev"
Requires-Dist: coverage==7.10.7; extra == "dev"
Requires-Dist: mypy==1.18.2; extra == "dev"
Requires-Dist: pytest==8.4.2; extra == "dev"
Requires-Dist: pytest-cov==7.0.0; extra == "dev"
Requires-Dist: pytest-sugar==1.1.1; extra == "dev"
Requires-Dist: ruff==0.13.2; extra == "dev"
Requires-Dist: mccabe==0.7.0; extra == "dev"
Requires-Dist: pandas-stubs==2.3.2.250926; extra == "dev"
Requires-Dist: sphinx==8.2.3; extra == "dev"
Requires-Dist: sphinx-autodoc-typehints==3.2.0; extra == "dev"
Requires-Dist: sphinx-rtd-theme==3.0.2; extra == "dev"
Requires-Dist: types-PyYAML==6.0.2; extra == "dev"
Requires-Dist: types-python-dateutil==2.9.0.20250822; extra == "dev"
Requires-Dist: tox==4.25.0; extra == "dev"
Provides-Extra: web
Requires-Dist: flask==3.1.2; extra == "web"
Requires-Dist: Flask-WTF==1.2.2; extra == "web"
Requires-Dist: wtforms==3.2.1; extra == "web"
Requires-Dist: werkzeug==3.1.3; extra == "web"
Requires-Dist: lxml==6.0.1; extra == "web"
Requires-Dist: gunicorn==23.0.0; extra == "web"
Dynamic: license-file
